olmoearth_run/__init__.py
olmoearth_run/config.py
olmoearth_run/runner/exceptions.py
olmoearth_run/runner/main.py
olmoearth_run/runner/callbacks/__init__.py
olmoearth_run/runner/callbacks/evaluation_metadata_writer.py
olmoearth_run/runner/local/fine_tune_runner.py
olmoearth_run/runner/local/predict_runner.py
olmoearth_run/runner/local/unified_config_finetune_runner.py
olmoearth_run/runner/local/unified_config_predict_runner.py
olmoearth_run/runner/local/unified_config_example/finetune.py
olmoearth_run/runner/metrics/create_partitions_metrics.py
olmoearth_run/runner/metrics/dataset_builder.py
olmoearth_run/runner/metrics/window_prep.py
olmoearth_run/runner/models/operational_context.py
olmoearth_run/runner/models/rslearn_config.py
olmoearth_run/runner/models/training/annotation_features.py
olmoearth_run/runner/models/training/labeled_data.py
olmoearth_run/runner/steps/base_step_definition.py
olmoearth_run/runner/steps/combine_partitions_step_definition.py
olmoearth_run/runner/steps/create_partitions_step_definition.py
olmoearth_run/runner/steps/dataset_build_from_windows_step_definition.py
olmoearth_run/runner/steps/dataset_build_step_definition.py
olmoearth_run/runner/steps/fine_tuning_step_definition.py
olmoearth_run/runner/steps/model_evaluation_step_definition.py
olmoearth_run/runner/steps/postprocess_partition_step_definition.py
olmoearth_run/runner/steps/prepare_labeled_windows_step_definition.py
olmoearth_run/runner/steps/run_inference_step_definition.py
olmoearth_run/runner/tools/dataset_builder.py
olmoearth_run/runner/tools/mask_utils.py
olmoearth_run/runner/tools/olmoearth_run_config_loader.py
olmoearth_run/runner/tools/converters/feature_collection.py
olmoearth_run/runner/tools/converters/st_geometry.py
olmoearth_run/runner/tools/data_splitters/data_splitter_interface.py
olmoearth_run/runner/tools/data_splitters/hash_assignment.py
olmoearth_run/runner/tools/data_splitters/random_data_splitter.py
olmoearth_runner-0.1.13.dist-info/licenses/LICENSE
olmoearth_runner-0.1.13.dist-info/METADATA
olmoearth_runner-0.1.13.dist-info/WHEEL
olmoearth_runner-0.1.13.dist-info/entry_points.txt
olmoearth_runner-0.1.13.dist-info/top_level.txt
olmoearth_runner-0.1.13.dist-info/RECORD
