Metadata-Version: 2.4
Name: olmoearth-runner
Version: 0.1.13
Summary: OlmoEarth Runner - Geospatial ML processing tools for distributed inference and training (runner components only)
Author: OlmoEarth Team
Classifier: Development Status :: 3 - Alpha
Classifier: Intended Audience :: Developers
Classifier: Intended Audience :: Science/Research
Classifier: Programming Language :: Python :: 3
Classifier: Programming Language :: Python :: 3.11
Classifier: Topic :: Scientific/Engineering :: GIS
Classifier: Topic :: Scientific/Engineering :: Artificial Intelligence
Requires-Python: <3.12,>=3.11
License-File: LICENSE
Requires-Dist: absl-py==2.3.1
Requires-Dist: accelerate==1.12.0
Requires-Dist: aenum==3.1.16
Requires-Dist: affine==2.4.0
Requires-Dist: aiobotocore==2.26.0
Requires-Dist: aiohappyeyeballs==2.6.1
Requires-Dist: aiohttp==3.13.2
Requires-Dist: aioitertools==0.13.0
Requires-Dist: aiosignal==1.4.0
Requires-Dist: albucore==0.0.16
Requires-Dist: albumentations==1.4.10
Requires-Dist: annotated-types==0.7.0
Requires-Dist: antlr4-python3-runtime==4.9.3
Requires-Dist: anyio==4.12.0
Requires-Dist: attrs==25.4.0
Requires-Dist: bitsandbytes==0.49.0; sys_platform != "darwin"
Requires-Dist: black==25.12.0
Requires-Dist: blinker==1.9.0
Requires-Dist: bmipy==2.0.1
Requires-Dist: boto3==1.41.5
Requires-Dist: botocore==1.41.5
Requires-Dist: cachetools==6.2.4
Requires-Dist: cdsapi==0.7.7
Requires-Dist: certifi==2025.11.12
Requires-Dist: cffi==2.0.0; platform_python_implementation != "PyPy"
Requires-Dist: cftime==1.6.5
Requires-Dist: charset-normalizer==3.4.4
Requires-Dist: click==8.3.1
Requires-Dist: click-plugins==1.1.1.2
Requires-Dist: cligj==0.7.2
Requires-Dist: colorama==0.4.6; sys_platform == "win32"
Requires-Dist: contourpy==1.3.3
Requires-Dist: cryptography==46.0.3
Requires-Dist: cycler==0.12.1
Requires-Dist: decorator==5.2.1
Requires-Dist: docstring-parser==0.17.0
Requires-Dist: earthdaily==1.5.1
Requires-Dist: earthengine-api==1.7.4
Requires-Dist: ecmwf-datastores-client==0.4.1
Requires-Dist: einops==0.8.1
Requires-Dist: filelock==3.20.1
Requires-Dist: fiona==1.10.1
Requires-Dist: flask==3.1.2
Requires-Dist: fonttools==4.61.1
Requires-Dist: frozenlist==1.8.0
Requires-Dist: fsspec==2025.12.0
Requires-Dist: gcsfs==2025.12.0
Requires-Dist: geojson==3.2.0
Requires-Dist: geojson-pydantic==2.1.0
Requires-Dist: geopandas==1.1.1
Requires-Dist: gitdb==4.0.12
Requires-Dist: gitpython==3.1.45
Requires-Dist: google-api-core==2.28.1
Requires-Dist: google-api-python-client==2.187.0
Requires-Dist: google-auth==2.45.0
Requires-Dist: google-auth-httplib2==0.3.0
Requires-Dist: google-auth-oauthlib==1.2.2
Requires-Dist: google-cloud-bigquery==3.39.0
Requires-Dist: google-cloud-core==2.5.0
Requires-Dist: google-cloud-storage==3.7.0
Requires-Dist: google-cloud-storage-control==1.8.0
Requires-Dist: google-crc32c==1.8.0
Requires-Dist: google-resumable-media==2.8.0
Requires-Dist: googleapis-common-protos==1.72.0
Requires-Dist: grpc-google-iam-v1==0.14.3
Requires-Dist: grpcio==1.76.0
Requires-Dist: grpcio-status==1.76.0
Requires-Dist: h11==0.16.0
Requires-Dist: h5py==3.15.1
Requires-Dist: hf-xet==1.2.0; platform_machine == "aarch64" or platform_machine == "amd64" or platform_machine == "arm64" or platform_machine == "x86_64"
Requires-Dist: httpcore==1.0.9
Requires-Dist: httplib2==0.31.0
Requires-Dist: httpx==0.28.1
Requires-Dist: huggingface-hub==0.36.0
Requires-Dist: hydra-core==1.3.2
Requires-Dist: idna==3.11
Requires-Dist: imageio==2.37.2
Requires-Dist: importlib-resources==6.5.2
Requires-Dist: itsdangerous==2.2.0
Requires-Dist: jinja2==3.1.6
Requires-Dist: jmespath==1.0.1
Requires-Dist: joblib==1.5.3
Requires-Dist: jsonargparse==4.35.0
Requires-Dist: jsonschema==4.25.1
Requires-Dist: jsonschema-specifications==2025.9.1
Requires-Dist: kiwisolver==1.4.9
Requires-Dist: kornia==0.8.2
Requires-Dist: kornia-rs==0.1.10
Requires-Dist: lazy-loader==0.4
Requires-Dist: lightly==1.5.22
Requires-Dist: lightly-utils==0.0.2
Requires-Dist: lightning==2.5.1.post0
Requires-Dist: lightning-utilities==0.15.2
Requires-Dist: lxml==6.0.2
Requires-Dist: markdown==3.10
Requires-Dist: markdown-it-py==4.0.0
Requires-Dist: markupsafe==3.0.3
Requires-Dist: matplotlib==3.10.8
Requires-Dist: mdurl==0.1.2
Requires-Dist: mpmath==1.3.0
Requires-Dist: multidict==6.7.0
Requires-Dist: multiurl==0.3.7
Requires-Dist: mypy-extensions==1.1.0
Requires-Dist: netcdf4==1.7.3
Requires-Dist: networkx==3.6.1
Requires-Dist: numpy==1.26.4
Requires-Dist: nvidia-cublas-cu12==12.6.4.1; platform_machine == "x86_64" and sys_platform == "linux"
Requires-Dist: nvidia-cuda-cupti-cu12==12.6.80; platform_machine == "x86_64" and sys_platform == "linux"
Requires-Dist: nvidia-cuda-nvrtc-cu12==12.6.77; platform_machine == "x86_64" and sys_platform == "linux"
Requires-Dist: nvidia-cuda-runtime-cu12==12.6.77; platform_machine == "x86_64" and sys_platform == "linux"
Requires-Dist: nvidia-cudnn-cu12==9.5.1.17; platform_machine == "x86_64" and sys_platform == "linux"
Requires-Dist: nvidia-cufft-cu12==11.3.0.4; platform_machine == "x86_64" and sys_platform == "linux"
Requires-Dist: nvidia-cufile-cu12==1.11.1.6; platform_machine == "x86_64" and sys_platform == "linux"
Requires-Dist: nvidia-curand-cu12==10.3.7.77; platform_machine == "x86_64" and sys_platform == "linux"
Requires-Dist: nvidia-cusolver-cu12==11.7.1.2; platform_machine == "x86_64" and sys_platform == "linux"
Requires-Dist: nvidia-cusparse-cu12==12.5.4.2; platform_machine == "x86_64" and sys_platform == "linux"
Requires-Dist: nvidia-cusparselt-cu12==0.6.3; platform_machine == "x86_64" and sys_platform == "linux"
Requires-Dist: nvidia-nccl-cu12==2.26.2; platform_machine == "x86_64" and sys_platform == "linux"
Requires-Dist: nvidia-nvjitlink-cu12==12.6.85; platform_machine == "x86_64" and sys_platform == "linux"
Requires-Dist: nvidia-nvtx-cu12==12.6.77; platform_machine == "x86_64" and sys_platform == "linux"
Requires-Dist: oauthlib==3.3.1
Requires-Dist: olmoearth-pretrain==0.0.2
Requires-Dist: omegaconf==2.3.0
Requires-Dist: opencv-python-headless==4.11.0.86
Requires-Dist: osmium==4.2.0
Requires-Dist: owslib==0.35.0
Requires-Dist: packaging==24.2
Requires-Dist: pandas==2.3.3
Requires-Dist: pathlib-abc==0.5.2
Requires-Dist: pathspec==0.12.1
Requires-Dist: pillow==11.3.0
Requires-Dist: planet==3.4.0
Requires-Dist: planet-auth==2.3.1
Requires-Dist: planetary-computer==1.0.0
Requires-Dist: platformdirs==4.5.1
Requires-Dist: prometheus-client==0.23.1
Requires-Dist: prompt-toolkit==3.0.52
Requires-Dist: propcache==0.4.1
Requires-Dist: proto-plus==1.27.0
Requires-Dist: protobuf==6.33.2
Requires-Dist: psutil==7.1.3
Requires-Dist: pyasn1==0.6.1
Requires-Dist: pyasn1-modules==0.4.2
Requires-Dist: pycocotools==2.0.11
Requires-Dist: pycparser==2.23; implementation_name != "PyPy" and platform_python_implementation != "PyPy"
Requires-Dist: pydantic==2.12.5
Requires-Dist: pydantic-core==2.41.5
Requires-Dist: pydantic-settings==2.12.0
Requires-Dist: pygments==2.19.2
Requires-Dist: pyjwt==2.10.1
Requires-Dist: pyogrio==0.12.1
Requires-Dist: pyparsing==3.2.5
Requires-Dist: pyproj==3.7.2
Requires-Dist: pyqrcode==1.2.1
Requires-Dist: pystac==1.14.1
Requires-Dist: pystac-client==0.9.0
Requires-Dist: python-box==7.3.2
Requires-Dist: python-dateutil==2.9.0.post0
Requires-Dist: python-dotenv==1.2.1
Requires-Dist: pytimeparse==1.1.8
Requires-Dist: pytokens==0.4.0
Requires-Dist: pytorch-lightning==2.6.0
Requires-Dist: pytz==2025.2
Requires-Dist: pyyaml==6.0.3
Requires-Dist: rasterio==1.4.4
Requires-Dist: referencing==0.37.0
Requires-Dist: regex==2025.11.3
Requires-Dist: requests==2.32.5
Requires-Dist: requests-oauthlib==2.0.0
Requires-Dist: rich==13.9.4
Requires-Dist: rioxarray==0.19.0
Requires-Dist: rpds-py==0.30.0
Requires-Dist: rsa==4.9.1
Requires-Dist: rslearn==0.0.26
Requires-Dist: rtree==1.4.1
Requires-Dist: s3fs==2025.12.0
Requires-Dist: s3transfer==0.15.0
Requires-Dist: safetensors==0.7.0
Requires-Dist: satlaspretrain-models==0.3.1
Requires-Dist: scikit-image==0.25.2
Requires-Dist: scikit-learn==1.8.0
Requires-Dist: scipy==1.16.3
Requires-Dist: segmentation-models-pytorch==0.5.0
Requires-Dist: sentry-sdk==2.48.0
Requires-Dist: setuptools==80.9.0
Requires-Dist: shapely==2.1.2
Requires-Dist: six==1.17.0
Requires-Dist: smmap==5.0.2
Requires-Dist: soilgrids==0.1.4
Requires-Dist: strenum==0.4.15
Requires-Dist: sympy==1.14.0
Requires-Dist: tenacity==9.1.2
Requires-Dist: tensorboard==2.20.0
Requires-Dist: tensorboard-data-server==0.7.2
Requires-Dist: tensorboardx==2.6.4
Requires-Dist: termcolor==3.2.0
Requires-Dist: terratorch==1.1.1
Requires-Dist: threadpoolctl==3.6.0
Requires-Dist: tifffile==2025.12.12
Requires-Dist: timm==1.0.22
Requires-Dist: tokenizers==0.22.1
Requires-Dist: toml==0.10.2
Requires-Dist: torch==2.7.1
Requires-Dist: torchgeo==0.7.1
Requires-Dist: torchmetrics==1.8.2
Requires-Dist: torchvision==0.22.1
Requires-Dist: tqdm==4.67.1
Requires-Dist: transformers==4.57.3
Requires-Dist: triton==3.3.1; platform_machine == "x86_64" and sys_platform == "linux"
Requires-Dist: typeshed-client==2.8.2
Requires-Dist: typing-extensions==4.15.0
Requires-Dist: typing-inspection==0.4.2
Requires-Dist: tzdata==2025.3
Requires-Dist: universal-pathlib==0.3.7
Requires-Dist: uritemplate==4.2.0
Requires-Dist: urllib3==2.6.2
Requires-Dist: wandb==0.23.1
Requires-Dist: wcwidth==0.2.14
Requires-Dist: werkzeug==3.1.4
Requires-Dist: wrapt==1.17.3
Requires-Dist: xarray==2025.12.0
Requires-Dist: yarl==1.22.0
Dynamic: license-file
